{
  "id": 67569441,
  "name": "youtubenode-app",
  "fullName": "Akad1070/youtubenode-app",
  "owner": {
    "login": "Akad1070",
    "id": 3106338,
    "avatarUrl": "https://avatars.githubusercontent.com/u/3106338?v=3",
    "gravatarId": "",
    "url": "https://api.github.com/users/Akad1070",
    "htmlUrl": "https://github.com/Akad1070",
    "followersUrl": "https://api.github.com/users/Akad1070/followers",
    "subscriptionsUrl": "https://api.github.com/users/Akad1070/subscriptions",
    "organizationsUrl": "https://api.github.com/users/Akad1070/orgs",
    "reposUrl": "https://api.github.com/users/Akad1070/repos",
    "receivedEventsUrl": "https://api.github.com/users/Akad1070/received_events",
    "type": "User"
  },
  "private": false,
  "htmlUrl": "https://github.com/Akad1070/youtubenode-app",
  "description": "My desktop application for a better usage of YouTube. Made with Electron and Youtube API",
  "fork": false,
  "url": "https://api.github.com/repos/Akad1070/youtubenode-app",
  "forksUrl": "https://api.github.com/repos/Akad1070/youtubenode-app/forks",
  "teamsUrl": "https://api.github.com/repos/Akad1070/youtubenode-app/teams",
  "hooksUrl": "https://api.github.com/repos/Akad1070/youtubenode-app/hooks",
  "eventsUrl": "https://api.github.com/repos/Akad1070/youtubenode-app/events",
  "tagsUrl": "https://api.github.com/repos/Akad1070/youtubenode-app/tags",
  "languagesUrl": "https://api.github.com/repos/Akad1070/youtubenode-app/languages",
  "stargazersUrl": "https://api.github.com/repos/Akad1070/youtubenode-app/stargazers",
  "contributorsUrl": "https://api.github.com/repos/Akad1070/youtubenode-app/contributors",
  "subscribersUrl": "https://api.github.com/repos/Akad1070/youtubenode-app/subscribers",
  "subscriptionUrl": "https://api.github.com/repos/Akad1070/youtubenode-app/subscription",
  "mergesUrl": "https://api.github.com/repos/Akad1070/youtubenode-app/merges",
  "downloadsUrl": "https://api.github.com/repos/Akad1070/youtubenode-app/downloads",
  "deploymentsUrl": "https://api.github.com/repos/Akad1070/youtubenode-app/deployments",
  "createdAt": "2016-09-07T03:41:22.000Z",
  "updatedAt": "2016-09-13T00:24:37.000Z",
  "pushedAt": "2016-10-16T16:26:39.000Z",
  "gitUrl": "git://github.com/Akad1070/youtubenode-app.git",
  "sshUrl": "git@github.com:Akad1070/youtubenode-app.git",
  "cloneUrl": "https://github.com/Akad1070/youtubenode-app.git",
  "svnUrl": "https://github.com/Akad1070/youtubenode-app",
  "homepage": null,
  "size": 45819,
  "stargazersCount": 0,
  "watchersCount": 0,
  "language": "CSS",
  "hasIssues": true,
  "hasDownloads": true,
  "hasWiki": true,
  "hasPages": false,
  "forksCount": 0,
  "mirrorUrl": null,
  "openIssuesCount": 0,
  "openIssues": 0,
  "watchers": 0,
  "defaultBranch": "master",
  "permissions": {
    "admin": false,
    "push": false,
    "pull": true
  },
  "license": {
    "key": "mit",
    "name": "MIT License",
    "spdxId": "MIT",
    "url": "https://api.github.com/licenses/mit",
    "featured": true
  },
  "networkCount": 0,
  "subscribersCount": 1,
  "status": 200,
  "packageJSON": {
    "name": "youtube-node-app",
    "version": "0.0.1",
    "description": "Litte Youtube App written with Electron and YoutubeDataAPI",
    "main": "./main.js",
    "scripts": {
      "package": "electron-packager ./ YoutubeNode --all --out ~/Desktop/YoutubeNodee --version 0.1 --overwrite --icon=./zapp/img/app-icon.icns",
      "server": "nodemon -V --watch server --exec babel-node --presets-react -- server/server.js",
      "start": "electron .",
      "test": "echo \"Error: no test specified\" && exit 1"
    },
    "repository": "https://github.com/Akad1070/youtubenode-app",
    "keywords": [
      "youtube",
      "node",
      "express",
      "react",
      "electron"
    ],
    "license": "MIT",
    "homepage": "https://github.com/Akad1070/youtubenode-app#readme",
    "devDependencies": {
      "babel-cli": "^6.16.0",
      "babel-core": "^6.17.0",
      "babel-loader": "^6.2.5",
      "babel-preset-es2015": "^6.16.0",
      "babel-preset-react": "^6.16.0",
      "electron-packager": "^5.0.1",
      "electron-prebuilt": "^1.3.5",
      "express": "^4.14.0",
      "nodemon": "^1.11.0",
      "react-hot-loader": "^1.3.0",
      "webpack": "^1.13.2",
      "webpack-dev-middleware": "^1.8.4",
      "webpack-hot-middleware": "^2.13.0"
    },
    "dependencies": {
      "axios": "^0.15.0",
      "babel-core": "^6.14.0",
      "babel-plugin-add-module-exports": "^0.1.2",
      "babel-plugin-react-html-attrs": "^2.0.0",
      "babel-plugin-transform-class-properties": "^6.3.13",
      "babel-plugin-transform-decorators-legacy": "^1.3.4",
      "babel-preset-es2015": "^6.3.13",
      "babel-preset-stage-0": "^6.3.13",
      "body-parser": "^1.15.2",
      "classnames": "^2.2.5",
      "electron": "^1.4.3",
      "jsonwebtoken": "^7.1.9",
      "lodash": "^4.16.4",
      "react": "^15.1.0",
      "react-dom": "^15.1.0",
      "react-google-login": "^2.5.2",
      "react-redux": "^4.4.5",
      "react-router": "^2.5.0",
      "redux": "^3.6.0",
      "redux-logger": "^2.7.0",
      "redux-thunk": "^2.1.0",
      "validator": "^6.0.0",
      "winston": "^2.2.0",
      "youtube-node": "^1.3.0"
    }
  },
  "packageStatus": 200,
  "contributors": [
    "Akad1070"
  ],
  "firstCommit": {
    "sha": "fc785220d73c6f5c112a82c75734e0438c42980c",
    "commit": {
      "author": {
        "name": "Akad1070",
        "email": "akad1070@users.noreply.github.com",
        "date": "2016-09-07T03:41:22Z"
      },
      "committer": {
        "name": "Akad1070",
        "email": "akad1070@users.noreply.github.com",
        "date": "2016-09-07T03:41:22Z"
      },
      "message": "Initial commit",
      "tree": {
        "sha": "0107fabc2c01d89ceda0060c1dd1efc4494299d4",
        "url": "https://api.github.com/repos/Dakad/youtubenode-app/git/trees/0107fabc2c01d89ceda0060c1dd1efc4494299d4"
      },
      "url": "https://api.github.com/repos/Dakad/youtubenode-app/git/commits/fc785220d73c6f5c112a82c75734e0438c42980c",
      "commentCount": 0
    }
  },
  "filename": "Akad1070___youtubenode-app.json",
  "releases": []
}