{
  "id": 39059370,
  "name": "menu",
  "fullName": "amonks/menu",
  "owner": {
    "login": "amonks",
    "id": 50010,
    "avatarUrl": "https://avatars.githubusercontent.com/u/50010?v=3",
    "gravatarId": "",
    "url": "https://api.github.com/users/amonks",
    "htmlUrl": "https://github.com/amonks",
    "followersUrl": "https://api.github.com/users/amonks/followers",
    "subscriptionsUrl": "https://api.github.com/users/amonks/subscriptions",
    "organizationsUrl": "https://api.github.com/users/amonks/orgs",
    "reposUrl": "https://api.github.com/users/amonks/repos",
    "receivedEventsUrl": "https://api.github.com/users/amonks/received_events",
    "type": "User"
  },
  "private": false,
  "description": "forked from example app @maxogden/menubar",
  "fork": false,
  "createdAt": "2015-07-14T07:03:17.000Z",
  "updatedAt": "2015-07-14T07:13:43.000Z",
  "pushedAt": "2015-07-14T07:21:17.000Z",
  "homepage": "",
  "size": 220,
  "stargazersCount": 0,
  "watchersCount": 0,
  "language": "JavaScript",
  "hasIssues": true,
  "hasDownloads": true,
  "hasWiki": true,
  "hasPages": false,
  "forksCount": 0,
  "openIssuesCount": 0,
  "openIssues": 0,
  "watchers": 0,
  "defaultBranch": "master",
  "permissions": {
    "admin": false,
    "push": false,
    "pull": true
  },
  "license": null,
  "networkCount": 0,
  "subscribersCount": 1,
  "status": 200,
  "packageJSON": {
    "name": "example-menubar-app",
    "version": "1.0.0",
    "description": "example menubar electron app",
    "dependencies": {
      "electron-debug": "^0.1.1",
      "jquery": "2.1.4",
      "menubar": "*"
    },
    "devDependencies": {
      "electron-packager": "^4.0.2",
      "electron-prebuilt": "0.26.1"
    },
    "main": "main.js",
    "scripts": {
      "build": "electron-packager . Example --platform=darwin --arch=x64 --version=0.26.0 --ignore=node_modules/electron --icon=Icon.icns",
      "start": "electron ."
    }
  },
  "packageStatus": 200,
  "contributors": [
    "amonks"
  ],
  "firstCommit": {
    "sha": "05f4c9f9813a757d6276b27d9347db4e20322723",
    "commit": {
      "author": {
        "name": "Andrew Monks",
        "email": "a@monks.co",
        "date": "2015-07-14T07:02:11Z"
      },
      "committer": {
        "name": "Andrew Monks",
        "email": "a@monks.co",
        "date": "2015-07-14T07:02:11Z"
      },
      "message": "initial commit: quit button!",
      "tree": {
        "sha": "f6b0ea20db7e0f0cf1af438f5850ce2b95e60b49",
        "url": "https://api.github.com/repos/amonks/menu/git/trees/f6b0ea20db7e0f0cf1af438f5850ce2b95e60b49"
      },
      "url": "https://api.github.com/repos/amonks/menu/git/commits/05f4c9f9813a757d6276b27d9347db4e20322723",
      "commentCount": 0
    }
  },
  "filename": "amonks___menu.json"
}