{
  "id": 51256314,
  "name": "Electron-Testapp",
  "fullName": "andiz81/Electron-Testapp",
  "owner": {
    "login": "andiz81",
    "id": 817009,
    "avatarUrl": "https://avatars.githubusercontent.com/u/817009?v=3",
    "gravatarId": "",
    "url": "https://api.github.com/users/andiz81",
    "htmlUrl": "https://github.com/andiz81",
    "followersUrl": "https://api.github.com/users/andiz81/followers",
    "subscriptionsUrl": "https://api.github.com/users/andiz81/subscriptions",
    "organizationsUrl": "https://api.github.com/users/andiz81/orgs",
    "reposUrl": "https://api.github.com/users/andiz81/repos",
    "receivedEventsUrl": "https://api.github.com/users/andiz81/received_events",
    "type": "User"
  },
  "private": false,
  "htmlUrl": "https://github.com/andiz81/Electron-Testapp",
  "description": null,
  "fork": false,
  "url": "https://api.github.com/repos/andiz81/Electron-Testapp",
  "forksUrl": "https://api.github.com/repos/andiz81/Electron-Testapp/forks",
  "teamsUrl": "https://api.github.com/repos/andiz81/Electron-Testapp/teams",
  "hooksUrl": "https://api.github.com/repos/andiz81/Electron-Testapp/hooks",
  "eventsUrl": "https://api.github.com/repos/andiz81/Electron-Testapp/events",
  "tagsUrl": "https://api.github.com/repos/andiz81/Electron-Testapp/tags",
  "languagesUrl": "https://api.github.com/repos/andiz81/Electron-Testapp/languages",
  "stargazersUrl": "https://api.github.com/repos/andiz81/Electron-Testapp/stargazers",
  "contributorsUrl": "https://api.github.com/repos/andiz81/Electron-Testapp/contributors",
  "subscribersUrl": "https://api.github.com/repos/andiz81/Electron-Testapp/subscribers",
  "subscriptionUrl": "https://api.github.com/repos/andiz81/Electron-Testapp/subscription",
  "mergesUrl": "https://api.github.com/repos/andiz81/Electron-Testapp/merges",
  "downloadsUrl": "https://api.github.com/repos/andiz81/Electron-Testapp/downloads",
  "deploymentsUrl": "https://api.github.com/repos/andiz81/Electron-Testapp/deployments",
  "createdAt": "2016-02-07T17:10:43.000Z",
  "updatedAt": "2016-02-07T17:39:18.000Z",
  "pushedAt": "2016-02-07T17:39:17.000Z",
  "gitUrl": "git://github.com/andiz81/Electron-Testapp.git",
  "sshUrl": "git@github.com:andiz81/Electron-Testapp.git",
  "cloneUrl": "https://github.com/andiz81/Electron-Testapp.git",
  "svnUrl": "https://github.com/andiz81/Electron-Testapp",
  "homepage": null,
  "size": 1,
  "stargazersCount": 0,
  "watchersCount": 0,
  "language": "JavaScript",
  "hasIssues": true,
  "hasDownloads": true,
  "hasWiki": true,
  "hasPages": false,
  "forksCount": 0,
  "mirrorUrl": null,
  "openIssuesCount": 0,
  "openIssues": 0,
  "watchers": 0,
  "defaultBranch": "master",
  "permissions": {
    "admin": false,
    "push": false,
    "pull": true
  },
  "license": null,
  "networkCount": 0,
  "subscribersCount": 1,
  "status": 200,
  "packageJSON": {
    "name": "create-multi-window-electron-app",
    "version": "0.1.0",
    "description": "",
    "main": "app.js",
    "scripts": {
      "start": "electron ."
    },
    "author": "Kyle Robinson Young <kyle@dontkry.com> (http://dontkry.com)",
    "license": "MIT",
    "devDependencies": {
      "electron-prebuilt": "^0.28.3",
      "electron-accelerator": "^0.0.5",
      "electron-packager": "^5.2.1"
    }
  },
  "packageStatus": 200
}