{
  "id": 72985533,
  "name": "notebooq",
  "fullName": "danielsneijers/notebooq",
  "owner": {
    "login": "danielsneijers",
    "id": 1942473,
    "avatarUrl": "https://avatars.githubusercontent.com/u/1942473?v=3",
    "gravatarId": "",
    "url": "https://api.github.com/users/danielsneijers",
    "htmlUrl": "https://github.com/danielsneijers",
    "followersUrl": "https://api.github.com/users/danielsneijers/followers",
    "subscriptionsUrl": "https://api.github.com/users/danielsneijers/subscriptions",
    "organizationsUrl": "https://api.github.com/users/danielsneijers/orgs",
    "reposUrl": "https://api.github.com/users/danielsneijers/repos",
    "receivedEventsUrl": "https://api.github.com/users/danielsneijers/received_events",
    "type": "User"
  },
  "private": false,
  "htmlUrl": "https://github.com/danielsneijers/notebooq",
  "description": "Markdown note taking for developers",
  "fork": false,
  "url": "https://api.github.com/repos/danielsneijers/notebooq",
  "forksUrl": "https://api.github.com/repos/danielsneijers/notebooq/forks",
  "teamsUrl": "https://api.github.com/repos/danielsneijers/notebooq/teams",
  "hooksUrl": "https://api.github.com/repos/danielsneijers/notebooq/hooks",
  "eventsUrl": "https://api.github.com/repos/danielsneijers/notebooq/events",
  "tagsUrl": "https://api.github.com/repos/danielsneijers/notebooq/tags",
  "languagesUrl": "https://api.github.com/repos/danielsneijers/notebooq/languages",
  "stargazersUrl": "https://api.github.com/repos/danielsneijers/notebooq/stargazers",
  "contributorsUrl": "https://api.github.com/repos/danielsneijers/notebooq/contributors",
  "subscribersUrl": "https://api.github.com/repos/danielsneijers/notebooq/subscribers",
  "subscriptionUrl": "https://api.github.com/repos/danielsneijers/notebooq/subscription",
  "mergesUrl": "https://api.github.com/repos/danielsneijers/notebooq/merges",
  "downloadsUrl": "https://api.github.com/repos/danielsneijers/notebooq/downloads",
  "deploymentsUrl": "https://api.github.com/repos/danielsneijers/notebooq/deployments",
  "createdAt": "2016-11-06T11:13:54.000Z",
  "updatedAt": "2016-11-06T11:14:30.000Z",
  "pushedAt": "2016-11-06T11:14:24.000Z",
  "gitUrl": "git://github.com/danielsneijers/notebooq.git",
  "sshUrl": "git@github.com:danielsneijers/notebooq.git",
  "cloneUrl": "https://github.com/danielsneijers/notebooq.git",
  "svnUrl": "https://github.com/danielsneijers/notebooq",
  "homepage": null,
  "size": 188,
  "stargazersCount": 0,
  "watchersCount": 0,
  "language": "JavaScript",
  "hasIssues": true,
  "hasDownloads": true,
  "hasWiki": true,
  "hasPages": false,
  "forksCount": 0,
  "mirrorUrl": null,
  "openIssuesCount": 0,
  "openIssues": 0,
  "watchers": 0,
  "defaultBranch": "master",
  "permissions": {
    "admin": false,
    "push": false,
    "pull": true
  },
  "license": null,
  "networkCount": 0,
  "subscribersCount": 0,
  "status": 200
}