{
  "id": 40232703,
  "name": "calculator",
  "fullName": "kaidesu/calculator",
  "owner": {
    "login": "kaidesu",
    "id": 355659,
    "avatarUrl": "https://avatars.githubusercontent.com/u/355659?v=3",
    "gravatarId": "",
    "url": "https://api.github.com/users/kaidesu",
    "htmlUrl": "https://github.com/kaidesu",
    "followersUrl": "https://api.github.com/users/kaidesu/followers",
    "subscriptionsUrl": "https://api.github.com/users/kaidesu/subscriptions",
    "organizationsUrl": "https://api.github.com/users/kaidesu/orgs",
    "reposUrl": "https://api.github.com/users/kaidesu/repos",
    "receivedEventsUrl": "https://api.github.com/users/kaidesu/received_events",
    "type": "User"
  },
  "private": false,
  "description": "Electron-based calculator app.",
  "fork": false,
  "createdAt": "2015-08-05T08:00:57.000Z",
  "updatedAt": "2015-08-05T08:06:32.000Z",
  "pushedAt": "2015-08-05T15:59:29.000Z",
  "homepage": null,
  "size": 172,
  "stargazersCount": 0,
  "watchersCount": 0,
  "language": "JavaScript",
  "hasIssues": true,
  "hasDownloads": true,
  "hasWiki": true,
  "hasPages": false,
  "forksCount": 1,
  "openIssuesCount": 0,
  "openIssues": 0,
  "watchers": 0,
  "defaultBranch": "master",
  "permissions": {
    "admin": false,
    "push": false,
    "pull": true
  },
  "license": null,
  "networkCount": 1,
  "subscribersCount": 1,
  "status": 200,
  "packageJSON": {
    "name": "Calculator",
    "version": "0.0.1",
    "description": "A simple calculator application built in Electron.",
    "main": "main.js",
    "scripts": {
      "start": "electron ."
    },
    "author": "Shea Lewis",
    "license": "MIT",
    "repository": {
      "type": "git",
      "url": "https://github.com/kaidesu/calculator"
    },
    "bugs": {
      "url": "https://github.com/kaidesu/calculator/issues"
    },
    "devDependencies": {
      "electron-prebuilt": "^0.30.2"
    }
  },
  "packageStatus": 200,
  "contributors": [
    "kaidesu"
  ]
}