{
  "id": 66906831,
  "name": "sound-machine-electron-guide",
  "fullName": "mamboer/sound-machine-electron-guide",
  "owner": {
    "login": "mamboer",
    "id": 85879,
    "avatarUrl": "https://avatars.githubusercontent.com/u/85879?v=3",
    "gravatarId": "",
    "url": "https://api.github.com/users/mamboer",
    "htmlUrl": "https://github.com/mamboer",
    "followersUrl": "https://api.github.com/users/mamboer/followers",
    "subscriptionsUrl": "https://api.github.com/users/mamboer/subscriptions",
    "organizationsUrl": "https://api.github.com/users/mamboer/orgs",
    "reposUrl": "https://api.github.com/users/mamboer/repos",
    "receivedEventsUrl": "https://api.github.com/users/mamboer/received_events",
    "type": "User"
  },
  "private": false,
  "description": "Accompanying repository for the Electron guide",
  "fork": true,
  "createdAt": "2016-08-30T04:35:32.000Z",
  "updatedAt": "2016-08-31T01:48:17.000Z",
  "pushedAt": "2016-08-31T01:53:01.000Z",
  "homepage": "https://medium.com/developers-writing/building-a-desktop-application-with-electron-204203eeb658#.9pl8yojiw",
  "size": 3620,
  "stargazersCount": 0,
  "watchersCount": 0,
  "language": "JavaScript",
  "hasIssues": false,
  "hasDownloads": true,
  "hasWiki": true,
  "hasPages": false,
  "forksCount": 0,
  "openIssuesCount": 0,
  "openIssues": 0,
  "watchers": 0,
  "defaultBranch": "master",
  "permissions": {
    "admin": false,
    "push": false,
    "pull": true
  },
  "license": null,
  "parent": {
    "id": 40200279,
    "name": "sound-machine-electron-guide",
    "fullName": "bojzi/sound-machine-electron-guide",
    "owner": {
      "login": "bojzi",
      "id": 54692,
      "avatarUrl": "https://avatars.githubusercontent.com/u/54692?v=3",
      "gravatarId": "",
      "url": "https://api.github.com/users/bojzi",
      "htmlUrl": "https://github.com/bojzi",
      "followersUrl": "https://api.github.com/users/bojzi/followers",
      "subscriptionsUrl": "https://api.github.com/users/bojzi/subscriptions",
      "organizationsUrl": "https://api.github.com/users/bojzi/orgs",
      "reposUrl": "https://api.github.com/users/bojzi/repos",
      "receivedEventsUrl": "https://api.github.com/users/bojzi/received_events",
      "type": "User"
    },
    "private": false,
    "htmlUrl": "https://github.com/bojzi/sound-machine-electron-guide",
    "description": "Accompanying repository for the Electron guide",
    "fork": false,
    "url": "https://api.github.com/repos/bojzi/sound-machine-electron-guide",
    "forksUrl": "https://api.github.com/repos/bojzi/sound-machine-electron-guide/forks",
    "teamsUrl": "https://api.github.com/repos/bojzi/sound-machine-electron-guide/teams",
    "hooksUrl": "https://api.github.com/repos/bojzi/sound-machine-electron-guide/hooks",
    "eventsUrl": "https://api.github.com/repos/bojzi/sound-machine-electron-guide/events",
    "tagsUrl": "https://api.github.com/repos/bojzi/sound-machine-electron-guide/tags",
    "languagesUrl": "https://api.github.com/repos/bojzi/sound-machine-electron-guide/languages",
    "stargazersUrl": "https://api.github.com/repos/bojzi/sound-machine-electron-guide/stargazers",
    "contributorsUrl": "https://api.github.com/repos/bojzi/sound-machine-electron-guide/contributors",
    "subscribersUrl": "https://api.github.com/repos/bojzi/sound-machine-electron-guide/subscribers",
    "subscriptionUrl": "https://api.github.com/repos/bojzi/sound-machine-electron-guide/subscription",
    "mergesUrl": "https://api.github.com/repos/bojzi/sound-machine-electron-guide/merges",
    "downloadsUrl": "https://api.github.com/repos/bojzi/sound-machine-electron-guide/downloads",
    "deploymentsUrl": "https://api.github.com/repos/bojzi/sound-machine-electron-guide/deployments",
    "createdAt": "2015-08-04T17:58:16.000Z",
    "updatedAt": "2016-09-01T07:28:57.000Z",
    "pushedAt": "2016-08-02T22:00:24.000Z",
    "gitUrl": "git://github.com/bojzi/sound-machine-electron-guide.git",
    "sshUrl": "git@github.com:bojzi/sound-machine-electron-guide.git",
    "cloneUrl": "https://github.com/bojzi/sound-machine-electron-guide.git",
    "svnUrl": "https://github.com/bojzi/sound-machine-electron-guide",
    "homepage": null,
    "size": 3534,
    "stargazersCount": 142,
    "watchersCount": 142,
    "language": "JavaScript",
    "hasIssues": true,
    "hasDownloads": true,
    "hasWiki": true,
    "hasPages": false,
    "forksCount": 62,
    "mirrorUrl": null,
    "openIssuesCount": 5,
    "openIssues": 5,
    "watchers": 142,
    "defaultBranch": "master"
  },
  "source": {
    "id": 40200279,
    "name": "sound-machine-electron-guide",
    "fullName": "bojzi/sound-machine-electron-guide",
    "owner": {
      "login": "bojzi",
      "id": 54692,
      "avatarUrl": "https://avatars.githubusercontent.com/u/54692?v=3",
      "gravatarId": "",
      "url": "https://api.github.com/users/bojzi",
      "htmlUrl": "https://github.com/bojzi",
      "followersUrl": "https://api.github.com/users/bojzi/followers",
      "subscriptionsUrl": "https://api.github.com/users/bojzi/subscriptions",
      "organizationsUrl": "https://api.github.com/users/bojzi/orgs",
      "reposUrl": "https://api.github.com/users/bojzi/repos",
      "receivedEventsUrl": "https://api.github.com/users/bojzi/received_events",
      "type": "User"
    },
    "private": false,
    "htmlUrl": "https://github.com/bojzi/sound-machine-electron-guide",
    "description": "Accompanying repository for the Electron guide",
    "fork": false,
    "url": "https://api.github.com/repos/bojzi/sound-machine-electron-guide",
    "forksUrl": "https://api.github.com/repos/bojzi/sound-machine-electron-guide/forks",
    "teamsUrl": "https://api.github.com/repos/bojzi/sound-machine-electron-guide/teams",
    "hooksUrl": "https://api.github.com/repos/bojzi/sound-machine-electron-guide/hooks",
    "eventsUrl": "https://api.github.com/repos/bojzi/sound-machine-electron-guide/events",
    "tagsUrl": "https://api.github.com/repos/bojzi/sound-machine-electron-guide/tags",
    "languagesUrl": "https://api.github.com/repos/bojzi/sound-machine-electron-guide/languages",
    "stargazersUrl": "https://api.github.com/repos/bojzi/sound-machine-electron-guide/stargazers",
    "contributorsUrl": "https://api.github.com/repos/bojzi/sound-machine-electron-guide/contributors",
    "subscribersUrl": "https://api.github.com/repos/bojzi/sound-machine-electron-guide/subscribers",
    "subscriptionUrl": "https://api.github.com/repos/bojzi/sound-machine-electron-guide/subscription",
    "mergesUrl": "https://api.github.com/repos/bojzi/sound-machine-electron-guide/merges",
    "downloadsUrl": "https://api.github.com/repos/bojzi/sound-machine-electron-guide/downloads",
    "deploymentsUrl": "https://api.github.com/repos/bojzi/sound-machine-electron-guide/deployments",
    "createdAt": "2015-08-04T17:58:16.000Z",
    "updatedAt": "2016-09-01T07:28:57.000Z",
    "pushedAt": "2016-08-02T22:00:24.000Z",
    "gitUrl": "git://github.com/bojzi/sound-machine-electron-guide.git",
    "sshUrl": "git@github.com:bojzi/sound-machine-electron-guide.git",
    "cloneUrl": "https://github.com/bojzi/sound-machine-electron-guide.git",
    "svnUrl": "https://github.com/bojzi/sound-machine-electron-guide",
    "homepage": null,
    "size": 3534,
    "stargazersCount": 142,
    "watchersCount": 142,
    "language": "JavaScript",
    "hasIssues": true,
    "hasDownloads": true,
    "hasWiki": true,
    "hasPages": false,
    "forksCount": 62,
    "mirrorUrl": null,
    "openIssuesCount": 5,
    "openIssues": 5,
    "watchers": 142,
    "defaultBranch": "master"
  },
  "networkCount": 62,
  "subscribersCount": 1,
  "status": 200,
  "packageJSON": {
    "name": "sound_machine",
    "version": "0.1.0",
    "main": "./main.js",
    "scripts": {
      "start": "electron .",
      "package": "electron-packager ./ SoundMachine --all --out ~/Desktop/SoundMachine --version 1.3.4 --overwrite --icon=./app/img/app-icon.icns"
    },
    "devDependencies": {
      "electron-packager": "^7.7.0",
      "electron-prebuilt": "^1.3.4"
    },
    "dependencies": {
      "nconf": "^0.8.4"
    }
  },
  "packageStatus": 200,
  "contributors": [
    "mamboer",
    "bojzi"
  ]
}