{
  "id": 53651716,
  "name": "Catify",
  "fullName": "MeoBeoI/Catify",
  "owner": {
    "login": "MeoBeoI",
    "id": 15938958,
    "avatarUrl": "https://avatars.githubusercontent.com/u/15938958?v=3",
    "gravatarId": "",
    "url": "https://api.github.com/users/MeoBeoI",
    "htmlUrl": "https://github.com/MeoBeoI",
    "followersUrl": "https://api.github.com/users/MeoBeoI/followers",
    "subscriptionsUrl": "https://api.github.com/users/MeoBeoI/subscriptions",
    "organizationsUrl": "https://api.github.com/users/MeoBeoI/orgs",
    "reposUrl": "https://api.github.com/users/MeoBeoI/repos",
    "receivedEventsUrl": "https://api.github.com/users/MeoBeoI/received_events",
    "type": "User"
  },
  "private": false,
  "htmlUrl": "https://github.com/MeoBeoI/Catify",
  "description": "Utility for Spotify, even your cat can use Spotify now !",
  "fork": false,
  "url": "https://api.github.com/repos/MeoBeoI/Catify",
  "forksUrl": "https://api.github.com/repos/MeoBeoI/Catify/forks",
  "teamsUrl": "https://api.github.com/repos/MeoBeoI/Catify/teams",
  "hooksUrl": "https://api.github.com/repos/MeoBeoI/Catify/hooks",
  "eventsUrl": "https://api.github.com/repos/MeoBeoI/Catify/events",
  "tagsUrl": "https://api.github.com/repos/MeoBeoI/Catify/tags",
  "languagesUrl": "https://api.github.com/repos/MeoBeoI/Catify/languages",
  "stargazersUrl": "https://api.github.com/repos/MeoBeoI/Catify/stargazers",
  "contributorsUrl": "https://api.github.com/repos/MeoBeoI/Catify/contributors",
  "subscribersUrl": "https://api.github.com/repos/MeoBeoI/Catify/subscribers",
  "subscriptionUrl": "https://api.github.com/repos/MeoBeoI/Catify/subscription",
  "mergesUrl": "https://api.github.com/repos/MeoBeoI/Catify/merges",
  "downloadsUrl": "https://api.github.com/repos/MeoBeoI/Catify/downloads",
  "deploymentsUrl": "https://api.github.com/repos/MeoBeoI/Catify/deployments",
  "createdAt": "2016-03-11T08:30:09.000Z",
  "updatedAt": "2016-11-14T15:45:21.000Z",
  "pushedAt": "2016-06-20T18:35:51.000Z",
  "gitUrl": "git://github.com/MeoBeoI/Catify.git",
  "sshUrl": "git@github.com:MeoBeoI/Catify.git",
  "cloneUrl": "https://github.com/MeoBeoI/Catify.git",
  "svnUrl": "https://github.com/MeoBeoI/Catify",
  "homepage": "",
  "size": 825,
  "stargazersCount": 27,
  "watchersCount": 27,
  "language": "JavaScript",
  "hasIssues": true,
  "hasDownloads": true,
  "hasWiki": true,
  "hasPages": false,
  "forksCount": 2,
  "mirrorUrl": null,
  "openIssuesCount": 0,
  "openIssues": 0,
  "watchers": 27,
  "defaultBranch": "master",
  "permissions": {
    "admin": false,
    "push": false,
    "pull": true
  },
  "license": {
    "key": "mit",
    "name": "MIT License",
    "spdxId": "MIT",
    "url": "https://api.github.com/licenses/mit",
    "featured": true
  },
  "networkCount": 2,
  "subscribersCount": 2,
  "status": 200
}