{
  "id": 42724488,
  "name": "DevpostFeed",
  "fullName": "nealrs/DevpostFeed",
  "owner": {
    "login": "nealrs",
    "id": 1568188,
    "avatarUrl": "https://avatars.githubusercontent.com/u/1568188?v=3",
    "gravatarId": "",
    "url": "https://api.github.com/users/nealrs",
    "htmlUrl": "https://github.com/nealrs",
    "followersUrl": "https://api.github.com/users/nealrs/followers",
    "subscriptionsUrl": "https://api.github.com/users/nealrs/subscriptions",
    "organizationsUrl": "https://api.github.com/users/nealrs/orgs",
    "reposUrl": "https://api.github.com/users/nealrs/repos",
    "receivedEventsUrl": "https://api.github.com/users/nealrs/received_events",
    "type": "User"
  },
  "private": false,
  "description": "An electron menubar app for your Devpost notification feed",
  "fork": false,
  "createdAt": "2015-09-18T13:40:45.000Z",
  "updatedAt": "2016-06-03T17:17:23.000Z",
  "pushedAt": "2015-09-19T15:21:38.000Z",
  "homepage": "http://devpost.com/software/devpost-notifications-electron-app",
  "size": 172,
  "stargazersCount": 1,
  "watchersCount": 1,
  "language": "JavaScript",
  "hasIssues": true,
  "hasDownloads": true,
  "hasWiki": true,
  "hasPages": false,
  "forksCount": 1,
  "openIssuesCount": 0,
  "openIssues": 0,
  "watchers": 1,
  "defaultBranch": "master",
  "permissions": {
    "admin": false,
    "push": false,
    "pull": true
  },
  "license": null,
  "networkCount": 1,
  "subscribersCount": 1,
  "status": 200,
  "packageJSON": {
    "name": "DevpostFeed",
    "repository": "https://github.com/nealrs/DevpostFeed",
    "version": "1.0.0",
    "description": "Electron tray app for Devpost notification feed",
    "main": "index.js",
    "scripts": {
      "test": "echo \"Error: no test specified\" && exit 1",
      "build": "electron-packager . DevpostFeed --platform=darwin --arch=x64 --version=1.00.0 --ignore=node_modules/electron --icon=Icon.icns",
      "start": "electron ."
    },
    "license": "ISC",
    "dependencies": {
      "assert": "1.3.0",
      "datauri": "latest",
      "menubar": "latest",
      "moment-timezone": "^0.4.0",
      "zombie": "latest"
    },
    "devDependencies": {
      "electron-packager": "^5.0.1",
      "electron-prebuilt": "0.30.3"
    }
  },
  "packageStatus": 200,
  "htmlUrl": "https://github.com/nealrs/DevpostFeed",
  "url": "https://api.github.com/repos/nealrs/DevpostFeed",
  "forksUrl": "https://api.github.com/repos/nealrs/DevpostFeed/forks",
  "teamsUrl": "https://api.github.com/repos/nealrs/DevpostFeed/teams",
  "hooksUrl": "https://api.github.com/repos/nealrs/DevpostFeed/hooks",
  "eventsUrl": "https://api.github.com/repos/nealrs/DevpostFeed/events",
  "tagsUrl": "https://api.github.com/repos/nealrs/DevpostFeed/tags",
  "languagesUrl": "https://api.github.com/repos/nealrs/DevpostFeed/languages",
  "stargazersUrl": "https://api.github.com/repos/nealrs/DevpostFeed/stargazers",
  "contributorsUrl": "https://api.github.com/repos/nealrs/DevpostFeed/contributors",
  "subscribersUrl": "https://api.github.com/repos/nealrs/DevpostFeed/subscribers",
  "subscriptionUrl": "https://api.github.com/repos/nealrs/DevpostFeed/subscription",
  "mergesUrl": "https://api.github.com/repos/nealrs/DevpostFeed/merges",
  "downloadsUrl": "https://api.github.com/repos/nealrs/DevpostFeed/downloads",
  "deploymentsUrl": "https://api.github.com/repos/nealrs/DevpostFeed/deployments",
  "gitUrl": "git://github.com/nealrs/DevpostFeed.git",
  "sshUrl": "git@github.com:nealrs/DevpostFeed.git",
  "cloneUrl": "https://github.com/nealrs/DevpostFeed.git",
  "svnUrl": "https://github.com/nealrs/DevpostFeed",
  "mirrorUrl": null,
  "contributors": [
    "nealrs"
  ],
  "firstCommit": {
    "sha": "b5d5a7840f57e9d07e01774f06c2b5d8a38424f2",
    "commit": {
      "author": {
        "name": "Neal Shyam",
        "email": "neal@audioshocker.com",
        "date": "2015-09-18T13:40:04Z"
      },
      "committer": {
        "name": "Neal Shyam",
        "email": "neal@audioshocker.com",
        "date": "2015-09-18T13:40:04Z"
      },
      "message": "load in",
      "tree": {
        "sha": "938d8ab129be74eca6c2799debf64daf7ab06b13",
        "url": "https://api.github.com/repos/nealrs/DevpostFeed/git/trees/938d8ab129be74eca6c2799debf64daf7ab06b13"
      },
      "url": "https://api.github.com/repos/nealrs/DevpostFeed/git/commits/b5d5a7840f57e9d07e01774f06c2b5d8a38424f2",
      "commentCount": 0
    }
  },
  "filename": "nealrs___DevpostFeed.json",
  "releases": []
}