{
  "id": 59045139,
  "name": "paex-desk",
  "fullName": "plesk/paex-desk",
  "owner": {
    "login": "plesk",
    "id": 6845467,
    "avatarUrl": "https://avatars.githubusercontent.com/u/6845467?v=3",
    "gravatarId": "",
    "url": "https://api.github.com/users/plesk",
    "htmlUrl": "https://github.com/plesk",
    "followersUrl": "https://api.github.com/users/plesk/followers",
    "subscriptionsUrl": "https://api.github.com/users/plesk/subscriptions",
    "organizationsUrl": "https://api.github.com/users/plesk/orgs",
    "reposUrl": "https://api.github.com/users/plesk/repos",
    "receivedEventsUrl": "https://api.github.com/users/plesk/received_events",
    "type": "Organization"
  },
  "private": false,
  "htmlUrl": "https://github.com/plesk/paex-desk",
  "description": "Plesk API Explorer Desktop App",
  "fork": false,
  "url": "https://api.github.com/repos/plesk/paex-desk",
  "forksUrl": "https://api.github.com/repos/plesk/paex-desk/forks",
  "teamsUrl": "https://api.github.com/repos/plesk/paex-desk/teams",
  "hooksUrl": "https://api.github.com/repos/plesk/paex-desk/hooks",
  "eventsUrl": "https://api.github.com/repos/plesk/paex-desk/events",
  "tagsUrl": "https://api.github.com/repos/plesk/paex-desk/tags",
  "languagesUrl": "https://api.github.com/repos/plesk/paex-desk/languages",
  "stargazersUrl": "https://api.github.com/repos/plesk/paex-desk/stargazers",
  "contributorsUrl": "https://api.github.com/repos/plesk/paex-desk/contributors",
  "subscribersUrl": "https://api.github.com/repos/plesk/paex-desk/subscribers",
  "subscriptionUrl": "https://api.github.com/repos/plesk/paex-desk/subscription",
  "mergesUrl": "https://api.github.com/repos/plesk/paex-desk/merges",
  "downloadsUrl": "https://api.github.com/repos/plesk/paex-desk/downloads",
  "deploymentsUrl": "https://api.github.com/repos/plesk/paex-desk/deployments",
  "createdAt": "2016-05-17T17:43:50.000Z",
  "updatedAt": "2016-05-21T09:08:28.000Z",
  "pushedAt": "2016-06-23T16:28:21.000Z",
  "gitUrl": "git://github.com/plesk/paex-desk.git",
  "sshUrl": "git@github.com:plesk/paex-desk.git",
  "cloneUrl": "https://github.com/plesk/paex-desk.git",
  "svnUrl": "https://github.com/plesk/paex-desk",
  "homepage": null,
  "size": 311,
  "stargazersCount": 2,
  "watchersCount": 2,
  "language": "JavaScript",
  "hasIssues": true,
  "hasDownloads": true,
  "hasWiki": true,
  "hasPages": true,
  "forksCount": 0,
  "mirrorUrl": null,
  "openIssuesCount": 1,
  "openIssues": 1,
  "watchers": 2,
  "defaultBranch": "master",
  "permissions": {
    "admin": false,
    "push": false,
    "pull": true
  },
  "license": null,
  "organization": {
    "login": "plesk",
    "id": 6845467,
    "avatarUrl": "https://avatars.githubusercontent.com/u/6845467?v=3",
    "gravatarId": "",
    "url": "https://api.github.com/users/plesk",
    "htmlUrl": "https://github.com/plesk",
    "followersUrl": "https://api.github.com/users/plesk/followers",
    "subscriptionsUrl": "https://api.github.com/users/plesk/subscriptions",
    "organizationsUrl": "https://api.github.com/users/plesk/orgs",
    "reposUrl": "https://api.github.com/users/plesk/repos",
    "receivedEventsUrl": "https://api.github.com/users/plesk/received_events",
    "type": "Organization"
  },
  "networkCount": 0,
  "subscribersCount": 10,
  "status": 200,
  "packageJSON": {
    "name": "paex-desk",
    "version": "1.2.0",
    "description": "Plesk API Explorer Desktop App",
    "main": "main.js",
    "scripts": {
      "start": "electron main.js"
    },
    "license": "Apache-2.0",
    "build": {
      "app-bundle-id": "com.plesk.paex-desk",
      "app-category-type": "public.app-category.developer-tools",
      "productName": "Plesk API Explorer",
      "osx": {
        "title": "Plesk API Explorer",
        "window": {
          "position": {
            "x": 250,
            "y": 250
          },
          "size": {
            "width": 540,
            "height": 340
          }
        }
      }
    },
    "devDependencies": {
      "electron-builder": "^3.25.0",
      "electron-packager": "^7.0.1",
      "electron-prebuilt": "^1.1.0",
      "plesk-api-client": "^1.0.0"
    }
  },
  "packageStatus": 200,
  "contributors": [
    "sibprogrammer"
  ],
  "firstCommit": {
    "sha": "2bba512511fc93f58eb2d4e8734d36882196cc6d",
    "commit": {
      "author": {
        "name": "Alexei Yuzhakov",
        "email": "sibprogrammer@gmail.com",
        "date": "2016-05-17T17:43:07Z"
      },
      "committer": {
        "name": "Alexei Yuzhakov",
        "email": "sibprogrammer@gmail.com",
        "date": "2016-05-17T17:43:07Z"
      },
      "message": "Initial import of the project.",
      "tree": {
        "sha": "bb1f7cf4a0e453dd697c655e4a344bbc34185206",
        "url": "https://api.github.com/repos/plesk/paex-desk/git/trees/bb1f7cf4a0e453dd697c655e4a344bbc34185206"
      },
      "url": "https://api.github.com/repos/plesk/paex-desk/git/commits/2bba512511fc93f58eb2d4e8734d36882196cc6d",
      "commentCount": 0
    }
  },
  "filename": "plesk___paex-desk.json",
  "releases": [
    {
      "url": "https://api.github.com/repos/plesk/paex-desk/releases/3285700",
      "assets": [
        {
          "url": "https://api.github.com/repos/plesk/paex-desk/releases/assets/1731419",
          "id": 1731419,
          "name": "paex-1.2.0.dmg",
          "label": null,
          "uploader": {
            "login": "sibprogrammer",
            "id": 187856,
            "avatarUrl": "https://avatars.githubusercontent.com/u/187856?v=3",
            "gravatarId": "",
            "url": "https://api.github.com/users/sibprogrammer",
            "htmlUrl": "https://github.com/sibprogrammer",
            "followersUrl": "https://api.github.com/users/sibprogrammer/followers",
            "subscriptionsUrl": "https://api.github.com/users/sibprogrammer/subscriptions",
            "organizationsUrl": "https://api.github.com/users/sibprogrammer/orgs",
            "reposUrl": "https://api.github.com/users/sibprogrammer/repos",
            "receivedEventsUrl": "https://api.github.com/users/sibprogrammer/received_events",
            "type": "User"
          },
          "contentType": "application/octet-stream",
          "state": "uploaded",
          "size": 47136546,
          "downloadCount": 5,
          "createdAt": "2016-05-23T17:13:39.000Z",
          "updatedAt": "2016-05-23T17:15:20.000Z",
          "browserDownloadUrl": "https://github.com/plesk/paex-desk/releases/download/1.2.0/paex-1.2.0.dmg"
        },
        {
          "url": "https://api.github.com/repos/plesk/paex-desk/releases/assets/1731409",
          "id": 1731409,
          "name": "paex-setup-1.2.0.exe",
          "label": null,
          "uploader": {
            "login": "sibprogrammer",
            "id": 187856,
            "avatarUrl": "https://avatars.githubusercontent.com/u/187856?v=3",
            "gravatarId": "",
            "url": "https://api.github.com/users/sibprogrammer",
            "htmlUrl": "https://github.com/sibprogrammer",
            "followersUrl": "https://api.github.com/users/sibprogrammer/followers",
            "subscriptionsUrl": "https://api.github.com/users/sibprogrammer/subscriptions",
            "organizationsUrl": "https://api.github.com/users/sibprogrammer/orgs",
            "reposUrl": "https://api.github.com/users/sibprogrammer/repos",
            "receivedEventsUrl": "https://api.github.com/users/sibprogrammer/received_events",
            "type": "User"
          },
          "contentType": "application/x-msdownload",
          "state": "uploaded",
          "size": 70358528,
          "downloadCount": 18,
          "createdAt": "2016-05-23T17:09:47.000Z",
          "updatedAt": "2016-05-23T17:13:33.000Z",
          "browserDownloadUrl": "https://github.com/plesk/paex-desk/releases/download/1.2.0/paex-setup-1.2.0.exe"
        }
      ],
      "assetsUrl": "https://api.github.com/repos/plesk/paex-desk/releases/3285700/assets",
      "htmlUrl": "https://github.com/plesk/paex-desk/releases/tag/1.2.0",
      "id": 3285700,
      "tagName": "1.2.0",
      "targetCommitish": "master",
      "name": "Plesk API Explorer Desktop App 1.2.0",
      "draft": false,
      "author": {
        "login": "sibprogrammer",
        "id": 187856,
        "avatarUrl": "https://avatars.githubusercontent.com/u/187856?v=3",
        "gravatarId": "",
        "url": "https://api.github.com/users/sibprogrammer",
        "htmlUrl": "https://github.com/sibprogrammer",
        "followersUrl": "https://api.github.com/users/sibprogrammer/followers",
        "subscriptionsUrl": "https://api.github.com/users/sibprogrammer/subscriptions",
        "organizationsUrl": "https://api.github.com/users/sibprogrammer/orgs",
        "reposUrl": "https://api.github.com/users/sibprogrammer/repos",
        "receivedEventsUrl": "https://api.github.com/users/sibprogrammer/received_events",
        "type": "User"
      },
      "prerelease": false,
      "createdAt": "2016-05-23T16:45:00.000Z",
      "publishedAt": "2016-05-24T01:19:34.000Z",
      "tarballUrl": "https://api.github.com/repos/plesk/paex-desk/tarball/1.2.0",
      "zipballUrl": "https://api.github.com/repos/plesk/paex-desk/zipball/1.2.0",
      "body": "Changelog:\n- Integrate advanced code editor\n- Add doc links\n"
    },
    {
      "url": "https://api.github.com/repos/plesk/paex-desk/releases/3272547",
      "assets": [
        {
          "url": "https://api.github.com/repos/plesk/paex-desk/releases/assets/1720242",
          "id": 1720242,
          "name": "paex-1.1.0.dmg",
          "label": null,
          "uploader": {
            "login": "sibprogrammer",
            "id": 187856,
            "avatarUrl": "https://avatars.githubusercontent.com/u/187856?v=3",
            "gravatarId": "",
            "url": "https://api.github.com/users/sibprogrammer",
            "htmlUrl": "https://github.com/sibprogrammer",
            "followersUrl": "https://api.github.com/users/sibprogrammer/followers",
            "subscriptionsUrl": "https://api.github.com/users/sibprogrammer/subscriptions",
            "organizationsUrl": "https://api.github.com/users/sibprogrammer/orgs",
            "reposUrl": "https://api.github.com/users/sibprogrammer/repos",
            "receivedEventsUrl": "https://api.github.com/users/sibprogrammer/received_events",
            "type": "User"
          },
          "contentType": "application/octet-stream",
          "state": "uploaded",
          "size": 47272887,
          "downloadCount": 4,
          "createdAt": "2016-05-20T17:44:41.000Z",
          "updatedAt": "2016-05-20T17:46:10.000Z",
          "browserDownloadUrl": "https://github.com/plesk/paex-desk/releases/download/1.1.0/paex-1.1.0.dmg"
        },
        {
          "url": "https://api.github.com/repos/plesk/paex-desk/releases/assets/1720247",
          "id": 1720247,
          "name": "paex-setup-1.1.0.exe",
          "label": null,
          "uploader": {
            "login": "sibprogrammer",
            "id": 187856,
            "avatarUrl": "https://avatars.githubusercontent.com/u/187856?v=3",
            "gravatarId": "",
            "url": "https://api.github.com/users/sibprogrammer",
            "htmlUrl": "https://github.com/sibprogrammer",
            "followersUrl": "https://api.github.com/users/sibprogrammer/followers",
            "subscriptionsUrl": "https://api.github.com/users/sibprogrammer/subscriptions",
            "organizationsUrl": "https://api.github.com/users/sibprogrammer/orgs",
            "reposUrl": "https://api.github.com/users/sibprogrammer/repos",
            "receivedEventsUrl": "https://api.github.com/users/sibprogrammer/received_events",
            "type": "User"
          },
          "contentType": "application/x-msdownload",
          "state": "uploaded",
          "size": 70054912,
          "downloadCount": 2,
          "createdAt": "2016-05-20T17:46:34.000Z",
          "updatedAt": "2016-05-20T17:51:45.000Z",
          "browserDownloadUrl": "https://github.com/plesk/paex-desk/releases/download/1.1.0/paex-setup-1.1.0.exe"
        }
      ],
      "assetsUrl": "https://api.github.com/repos/plesk/paex-desk/releases/3272547/assets",
      "htmlUrl": "https://github.com/plesk/paex-desk/releases/tag/1.1.0",
      "id": 3272547,
      "tagName": "1.1.0",
      "targetCommitish": "master",
      "name": "Plesk API Explorer Desktop App 1.1.0",
      "draft": false,
      "author": {
        "login": "sibprogrammer",
        "id": 187856,
        "avatarUrl": "https://avatars.githubusercontent.com/u/187856?v=3",
        "gravatarId": "",
        "url": "https://api.github.com/users/sibprogrammer",
        "htmlUrl": "https://github.com/sibprogrammer",
        "followersUrl": "https://api.github.com/users/sibprogrammer/followers",
        "subscriptionsUrl": "https://api.github.com/users/sibprogrammer/subscriptions",
        "organizationsUrl": "https://api.github.com/users/sibprogrammer/orgs",
        "reposUrl": "https://api.github.com/users/sibprogrammer/repos",
        "receivedEventsUrl": "https://api.github.com/users/sibprogrammer/received_events",
        "type": "User"
      },
      "prerelease": false,
      "createdAt": "2016-05-20T17:37:43.000Z",
      "publishedAt": "2016-05-20T17:52:22.000Z",
      "tarballUrl": "https://api.github.com/repos/plesk/paex-desk/tarball/1.1.0",
      "zipballUrl": "https://api.github.com/repos/plesk/paex-desk/zipball/1.1.0",
      "body": "Changelog:\n- Add ability to copy/paste text\n- Add ability to submit request by Cmd+Enter (Ctrl+Enter)\n"
    },
    {
      "url": "https://api.github.com/repos/plesk/paex-desk/releases/3263857",
      "assets": [
        {
          "url": "https://api.github.com/repos/plesk/paex-desk/releases/assets/1712967",
          "id": 1712967,
          "name": "paex-1.0.0.dmg",
          "label": null,
          "uploader": {
            "login": "sibprogrammer",
            "id": 187856,
            "avatarUrl": "https://avatars.githubusercontent.com/u/187856?v=3",
            "gravatarId": "",
            "url": "https://api.github.com/users/sibprogrammer",
            "htmlUrl": "https://github.com/sibprogrammer",
            "followersUrl": "https://api.github.com/users/sibprogrammer/followers",
            "subscriptionsUrl": "https://api.github.com/users/sibprogrammer/subscriptions",
            "organizationsUrl": "https://api.github.com/users/sibprogrammer/orgs",
            "reposUrl": "https://api.github.com/users/sibprogrammer/repos",
            "receivedEventsUrl": "https://api.github.com/users/sibprogrammer/received_events",
            "type": "User"
          },
          "contentType": "application/octet-stream",
          "state": "uploaded",
          "size": 51512289,
          "downloadCount": 5,
          "createdAt": "2016-05-19T18:03:18.000Z",
          "updatedAt": "2016-05-19T18:04:57.000Z",
          "browserDownloadUrl": "https://github.com/plesk/paex-desk/releases/download/1.0.0/paex-1.0.0.dmg"
        },
        {
          "url": "https://api.github.com/repos/plesk/paex-desk/releases/assets/1712968",
          "id": 1712968,
          "name": "paex-setup-1.0.0.exe",
          "label": null,
          "uploader": {
            "login": "sibprogrammer",
            "id": 187856,
            "avatarUrl": "https://avatars.githubusercontent.com/u/187856?v=3",
            "gravatarId": "",
            "url": "https://api.github.com/users/sibprogrammer",
            "htmlUrl": "https://github.com/sibprogrammer",
            "followersUrl": "https://api.github.com/users/sibprogrammer/followers",
            "subscriptionsUrl": "https://api.github.com/users/sibprogrammer/subscriptions",
            "organizationsUrl": "https://api.github.com/users/sibprogrammer/orgs",
            "reposUrl": "https://api.github.com/users/sibprogrammer/repos",
            "receivedEventsUrl": "https://api.github.com/users/sibprogrammer/received_events",
            "type": "User"
          },
          "contentType": "application/x-msdownload",
          "state": "uploaded",
          "size": 70135808,
          "downloadCount": 2,
          "createdAt": "2016-05-19T18:03:25.000Z",
          "updatedAt": "2016-05-19T18:09:41.000Z",
          "browserDownloadUrl": "https://github.com/plesk/paex-desk/releases/download/1.0.0/paex-setup-1.0.0.exe"
        }
      ],
      "assetsUrl": "https://api.github.com/repos/plesk/paex-desk/releases/3263857/assets",
      "htmlUrl": "https://github.com/plesk/paex-desk/releases/tag/1.0.0",
      "id": 3263857,
      "tagName": "1.0.0",
      "targetCommitish": "master",
      "name": "Plesk API Explorer Desktop App 1.0.0",
      "draft": false,
      "author": {
        "login": "sibprogrammer",
        "id": 187856,
        "avatarUrl": "https://avatars.githubusercontent.com/u/187856?v=3",
        "gravatarId": "",
        "url": "https://api.github.com/users/sibprogrammer",
        "htmlUrl": "https://github.com/sibprogrammer",
        "followersUrl": "https://api.github.com/users/sibprogrammer/followers",
        "subscriptionsUrl": "https://api.github.com/users/sibprogrammer/subscriptions",
        "organizationsUrl": "https://api.github.com/users/sibprogrammer/orgs",
        "reposUrl": "https://api.github.com/users/sibprogrammer/repos",
        "receivedEventsUrl": "https://api.github.com/users/sibprogrammer/received_events",
        "type": "User"
      },
      "prerelease": false,
      "createdAt": "2016-05-19T17:46:44.000Z",
      "publishedAt": "2016-05-19T18:09:41.000Z",
      "tarballUrl": "https://api.github.com/repos/plesk/paex-desk/tarball/1.0.0",
      "zipballUrl": "https://api.github.com/repos/plesk/paex-desk/zipball/1.0.0",
      "body": "First release.\n"
    }
  ]
}