{
  "id": 50091203,
  "name": "firejune_study",
  "fullName": "thirdj/firejune_study",
  "owner": {
    "login": "thirdj",
    "id": 1095127,
    "avatarUrl": "https://avatars.githubusercontent.com/u/1095127?v=3",
    "gravatarId": "",
    "url": "https://api.github.com/users/thirdj",
    "htmlUrl": "https://github.com/thirdj",
    "followersUrl": "https://api.github.com/users/thirdj/followers",
    "subscriptionsUrl": "https://api.github.com/users/thirdj/subscriptions",
    "organizationsUrl": "https://api.github.com/users/thirdj/orgs",
    "reposUrl": "https://api.github.com/users/thirdj/repos",
    "receivedEventsUrl": "https://api.github.com/users/thirdj/received_events",
    "type": "User"
  },
  "private": false,
  "htmlUrl": "https://github.com/thirdj/firejune_study",
  "description": "rsupport firejune react study",
  "fork": false,
  "url": "https://api.github.com/repos/thirdj/firejune_study",
  "forksUrl": "https://api.github.com/repos/thirdj/firejune_study/forks",
  "teamsUrl": "https://api.github.com/repos/thirdj/firejune_study/teams",
  "hooksUrl": "https://api.github.com/repos/thirdj/firejune_study/hooks",
  "eventsUrl": "https://api.github.com/repos/thirdj/firejune_study/events",
  "tagsUrl": "https://api.github.com/repos/thirdj/firejune_study/tags",
  "languagesUrl": "https://api.github.com/repos/thirdj/firejune_study/languages",
  "stargazersUrl": "https://api.github.com/repos/thirdj/firejune_study/stargazers",
  "contributorsUrl": "https://api.github.com/repos/thirdj/firejune_study/contributors",
  "subscribersUrl": "https://api.github.com/repos/thirdj/firejune_study/subscribers",
  "subscriptionUrl": "https://api.github.com/repos/thirdj/firejune_study/subscription",
  "mergesUrl": "https://api.github.com/repos/thirdj/firejune_study/merges",
  "downloadsUrl": "https://api.github.com/repos/thirdj/firejune_study/downloads",
  "deploymentsUrl": "https://api.github.com/repos/thirdj/firejune_study/deployments",
  "createdAt": "2016-01-21T07:51:00.000Z",
  "updatedAt": "2016-01-21T07:59:01.000Z",
  "pushedAt": "2016-01-21T08:12:36.000Z",
  "gitUrl": "git://github.com/thirdj/firejune_study.git",
  "sshUrl": "git@github.com:thirdj/firejune_study.git",
  "cloneUrl": "https://github.com/thirdj/firejune_study.git",
  "svnUrl": "https://github.com/thirdj/firejune_study",
  "homepage": null,
  "size": 4,
  "stargazersCount": 0,
  "watchersCount": 0,
  "language": "JavaScript",
  "hasIssues": true,
  "hasDownloads": true,
  "hasWiki": true,
  "hasPages": false,
  "forksCount": 0,
  "mirrorUrl": null,
  "openIssuesCount": 0,
  "openIssues": 0,
  "watchers": 0,
  "defaultBranch": "master",
  "permissions": {
    "admin": false,
    "push": false,
    "pull": true
  },
  "license": {
    "key": "mit",
    "name": "MIT License",
    "spdxId": "MIT",
    "url": "https://api.github.com/licenses/mit",
    "featured": true
  },
  "networkCount": 0,
  "subscribersCount": 1,
  "status": 200,
  "packageJSON": {
    "name": "firejune_study",
    "version": "0.0.1",
    "description": "ex1",
    "main": "main.js",
    "respository": {
      "type": "git",
      "url": "https://github.com/thirdj/firejune_study.git"
    },
    "dependencies": {
      "react": "*",
      "react-dom": "*",
      "node-jsx": "*",
      "jquery": "^1.8.3"
    },
    "devDependencies": {
      "electron-prebuilt": "0.36.*"
    },
    "scripts": {
      "test": "echo \"Error: no test specified\" && exit 1",
      "start": "electron ."
    },
    "license": "MIT"
  },
  "packageStatus": 200,
  "contributors": [
    "thirdj"
  ],
  "firstCommit": {
    "sha": "38fcb121e21ab00d07c6419b1c37642f8926ac62",
    "commit": {
      "author": {
        "name": "Choi, Jaehee",
        "email": "thirdjj@gmail.com",
        "date": "2016-01-21T07:51:01Z"
      },
      "committer": {
        "name": "Choi, Jaehee",
        "email": "thirdjj@gmail.com",
        "date": "2016-01-21T07:51:01Z"
      },
      "message": "Initial commit",
      "tree": {
        "sha": "85b7349835f696543121a1fafe56d7b7dc22b976",
        "url": "https://api.github.com/repos/thirdj/firejune_study/git/trees/85b7349835f696543121a1fafe56d7b7dc22b976"
      },
      "url": "https://api.github.com/repos/thirdj/firejune_study/git/commits/38fcb121e21ab00d07c6419b1c37642f8926ac62",
      "commentCount": 0
    }
  },
  "filename": "thirdj___firejune_study.json",
  "releases": []
}