{
  "id": 61048003,
  "name": "ncalc",
  "fullName": "Wares360/ncalc",
  "owner": {
    "login": "Wares360",
    "id": 7694303,
    "avatarUrl": "https://avatars.githubusercontent.com/u/7694303?v=3",
    "gravatarId": "",
    "url": "https://api.github.com/users/Wares360",
    "htmlUrl": "https://github.com/Wares360",
    "followersUrl": "https://api.github.com/users/Wares360/followers",
    "subscriptionsUrl": "https://api.github.com/users/Wares360/subscriptions",
    "organizationsUrl": "https://api.github.com/users/Wares360/orgs",
    "reposUrl": "https://api.github.com/users/Wares360/repos",
    "receivedEventsUrl": "https://api.github.com/users/Wares360/received_events",
    "type": "User"
  },
  "private": false,
  "htmlUrl": "https://github.com/Wares360/ncalc",
  "description": null,
  "fork": false,
  "url": "https://api.github.com/repos/Wares360/ncalc",
  "forksUrl": "https://api.github.com/repos/Wares360/ncalc/forks",
  "teamsUrl": "https://api.github.com/repos/Wares360/ncalc/teams",
  "hooksUrl": "https://api.github.com/repos/Wares360/ncalc/hooks",
  "eventsUrl": "https://api.github.com/repos/Wares360/ncalc/events",
  "tagsUrl": "https://api.github.com/repos/Wares360/ncalc/tags",
  "languagesUrl": "https://api.github.com/repos/Wares360/ncalc/languages",
  "stargazersUrl": "https://api.github.com/repos/Wares360/ncalc/stargazers",
  "contributorsUrl": "https://api.github.com/repos/Wares360/ncalc/contributors",
  "subscribersUrl": "https://api.github.com/repos/Wares360/ncalc/subscribers",
  "subscriptionUrl": "https://api.github.com/repos/Wares360/ncalc/subscription",
  "mergesUrl": "https://api.github.com/repos/Wares360/ncalc/merges",
  "downloadsUrl": "https://api.github.com/repos/Wares360/ncalc/downloads",
  "deploymentsUrl": "https://api.github.com/repos/Wares360/ncalc/deployments",
  "createdAt": "2016-06-13T15:33:59.000Z",
  "updatedAt": "2016-06-19T19:45:57.000Z",
  "pushedAt": "2016-06-24T16:56:32.000Z",
  "gitUrl": "git://github.com/Wares360/ncalc.git",
  "sshUrl": "git@github.com:Wares360/ncalc.git",
  "cloneUrl": "https://github.com/Wares360/ncalc.git",
  "svnUrl": "https://github.com/Wares360/ncalc",
  "homepage": null,
  "size": 953,
  "stargazersCount": 0,
  "watchersCount": 0,
  "language": "TypeScript",
  "hasIssues": true,
  "hasDownloads": true,
  "hasWiki": true,
  "hasPages": false,
  "forksCount": 0,
  "mirrorUrl": null,
  "openIssuesCount": 0,
  "openIssues": 0,
  "watchers": 0,
  "defaultBranch": "master",
  "permissions": {
    "admin": false,
    "push": false,
    "pull": true
  },
  "license": null,
  "networkCount": 0,
  "subscribersCount": 1,
  "status": 200,
  "packageJSON": {
    "name": "ncalc",
    "version": "1.0.0",
    "description": "",
    "main": "app/index.js",
    "repository": {
      "type": "git",
      "url": "git+https://github.com/Wares360/ncalc.git"
    },
    "author": "Nicholas Erhard",
    "license": "MIT",
    "dependencies": {
      "bootstrap": "^3.3.6",
      "mathquill": "^0.10.1-a",
      "jquery": "1.9.1"
    },
    "devDependencies": {
      "electron-prebuilt": "^1.2.2",
      "typescript": "^1.8.10",
      "gulp": "^3.9.1",
      "gulp-sass": "^2.3.1",
      "gulp-typescript": "^2.13.6",
      "gulp-sourcemaps": "^1.6.0",
      "gulp-relative-sourcemaps-source": "^0.1.2",
      "gulp-concat": "^2.6.0"
    }
  },
  "packageStatus": 200,
  "contributors": [
    "Wares360"
  ]
}